MANIFEST.in
README.md
setup.py
sphinx_vlaamsecodex.egg-info/PKG-INFO
sphinx_vlaamsecodex.egg-info/SOURCES.txt
sphinx_vlaamsecodex.egg-info/dependency_links.txt
sphinx_vlaamsecodex.egg-info/not-zip-safe
sphinx_vlaamsecodex.egg-info/requires.txt
sphinx_vlaamsecodex.egg-info/top_level.txt
sphinxcontrib/__init__.py
sphinxcontrib/sphinx-vlaamsecodex.py