Metadata-Version: 1.1
Name: sphinx-vlaamsecodex
Version: 0.2.4
Summary: Sphinx extension to integrate http://codex.vlaanderen.be in a document.
Home-page: https://github.com/OnroerendErfgoed/sphinx-vlaamsecodex
Author: Flanders Heritage Agency
Author-email: ict@onroerenderfgoed.be
License: MIT
Platform: any
Classifier: Programming Language :: Python :: 2.7
Classifier: Programming Language :: Python :: 3
Classifier: Environment :: Console
Classifier: Environment :: Web Environment
Classifier: Topic :: Documentation
Classifier: Topic :: Software Development :: Documentation
